test/__init__.py
test/test.py
w24thr-1.0.0.dist-info/METADATA
w24thr-1.0.0.dist-info/WHEEL
w24thr-1.0.0.dist-info/top_level.txt
w24thr-1.0.0.dist-info/RECORD
