Metadata-Version: 2.1
Name: w24thr
Version: 1.0.0
Summary: Demo Package for w24thr Article.
Home-page: https://github.com/jc3wrld999/w24thr
Author: jc3wrld999
Author-email: jc3wrld999@gmail.com
License: MIT
Keywords: test
Platform: UNKNOWN
